armis_sdk/__init__.py
armis_sdk/clients/__init__.py
armis_sdk/clients/assets_client.py
armis_sdk/clients/collectors_client.py
armis_sdk/clients/data_export_client.py
armis_sdk/clients/device_custom_properties_client.py
armis_sdk/clients/sites_client.py
armis_sdk/core/__init__.py
armis_sdk/core/armis_auth.py
armis_sdk/core/armis_client.py
armis_sdk/core/armis_error.py
armis_sdk/core/armis_sdk.py
armis_sdk/core/base_entity.py
armis_sdk/core/base_entity_client.py
armis_sdk/core/client_credentials.py
armis_sdk/core/response_utils.py
armis_sdk/entities/__init__.py
armis_sdk/entities/asq_rule.py
armis_sdk/entities/asset.py
armis_sdk/entities/asset_field_description.py
armis_sdk/entities/boundary.py
armis_sdk/entities/collector_image.py
armis_sdk/entities/data_export/__init__.py
armis_sdk/entities/data_export/application.py
armis_sdk/entities/data_export/base_exported_entity.py
armis_sdk/entities/data_export/data_export.py
armis_sdk/entities/data_export/risk_factor.py
armis_sdk/entities/data_export/vulnerability.py
armis_sdk/entities/device.py
armis_sdk/entities/device_custom_property.py
armis_sdk/entities/download_progress.py
armis_sdk/entities/network_interface.py
armis_sdk/entities/site.py
armis_sdk/types/__init__.py
armis_sdk/types/asset_id_source.py
armis_sdk/types/collector_image_type.py
armis_sdk-1.1.0.dist-info/METADATA
armis_sdk-1.1.0.dist-info/WHEEL
armis_sdk-1.1.0.dist-info/licenses/LICENSE
armis_sdk-1.1.0.dist-info/RECORD
