Metadata-Version: 2.4
Name: armis_sdk
Version: 1.1.0
Summary: The Armis SDK is a package that encapsulates common use-cases for interacting with the Armis platform.
License-File: LICENSE
Author: Shai Lachmanovich
Author-email: shai@armis.com
Requires-Python: >=3.9
Classifier: Programming Language :: Python :: 3
Classifier: Programming Language :: Python :: 3.9
Classifier: Programming Language :: Python :: 3.10
Classifier: Programming Language :: Python :: 3.11
Classifier: Programming Language :: Python :: 3.12
Classifier: Programming Language :: Python :: 3.13
Classifier: Programming Language :: Python :: 3.14
Requires-Dist: httpx
Requires-Dist: httpx-retries
Requires-Dist: pandas
Requires-Dist: pyarrow
Requires-Dist: pydantic
Requires-Dist: universalasync
